test4.v
module sync( clk, reset, q);
    input clk, reset;
    output reg [3:0] q;
    always @(posedge clk)
        begin
            if(reset)
                q=4'b0000;
            else    
                q<=q+4'd1;
        end
    
endmodule

module stimulus;
    reg clk, reset;
    wire [3:0] q;

    
    sync s(clk , reset, q);

    initial     
        begin
          clk=1'b0;
          forever
            begin #10 clk=~clk;
            end
        end

    initial 
        begin   
            $dumpfile("test4.vcd");
            $dumpvars(1, stimulus);
            reset=1'b1;
            #20 reset=1'b0;
            #200
            $finish;
        end
    initial 
        $monitor($time, "%d", q);

endmodule

test4.vcd
$date
	Mon Nov 18 12:52:42 2019
$end
$version
	Icarus Verilog
$end
$timescale
	1s
$end
$scope module stimulus $end
$var wire 4 ! q [3:0] $end
$var reg 1 " clk $end
$var reg 1 # reset $end
$upscope $end
$enddefinitions $end
#0
$dumpvars
1#
0"
bx !
$end
#10
b0 !
1"
#20
0"
0#
#30
b1 !
1"
#40
0"
#50
b10 !
1"
#60
0"
#70
b11 !
1"
#80
0"
#90
b100 !
1"
#100
0"
#110
b101 !
1"
#120
0"
#130
b110 !
1"
#140
0"
#150
b111 !
1"
#160
0"
#170
b1000 !
1"
#180
0"
#190
b1001 !
1"
#200
0"
#210
b1010 !
1"
